LICENSE
MANIFEST.in
README.md
README.rst
setup.py
PyIdGen.egg-info/PKG-INFO
PyIdGen.egg-info/SOURCES.txt
PyIdGen.egg-info/dependency_links.txt
PyIdGen.egg-info/top_level.txt
pyidgen/__init__.py
pyidgen/company.py
pyidgen/creditcard.py
pyidgen/driverlicense.py
pyidgen/occupation.py
pyidgen/person.py
pyidgen/phone.py
pyidgen/postaladdress.py
pyidgen/profile.py
pyidgen/ssn.py
pyidgen/useraccount.py
tests/test.py