Metadata-Version: 1.1
Name: PyIdGen
Version: 1.2
Summary: User Profile Generation Library for Quality Assurance and Information Security Testing
Home-page: https://github.com/greenpau/PyIdGen
Author: Paul Greenberg
Author-email: paul@greenberg.pro
License: GPLv3
Download-URL: http://pypi.python.org/packages/source/P/PyIdGen/PyIdGen-1.2.tar.gz
Platform: any
Classifier: Development Status :: 2 - Pre-Alpha
Classifier: Programming Language :: Python
Classifier: Programming Language :: Python :: 3
Classifier: Programming Language :: Python :: 3.0
Classifier: Programming Language :: Python :: 3.1
Classifier: Programming Language :: Python :: 3.2
Classifier: Programming Language :: Python :: 3.3
Classifier: Programming Language :: Python :: 3.4
Classifier: Topic :: Software Development
Classifier: Topic :: Software Development :: Testing
Classifier: Topic :: Software Development :: Quality Assurance
Classifier: Topic :: Software Development :: User Interfaces
Classifier: Topic :: Security
Classifier: Operating System :: OS Independent
Classifier: Intended Audience :: System Administrators
Classifier: Intended Audience :: Information Technology
Classifier: Intended Audience :: Developers
Classifier: License :: OSI Approved :: GNU General Public License v3 (GPLv3)
Classifier: License :: OSI Approved :: GNU General Public License v3 or later (GPLv3+)
